fileguard/__init__.py
fileguard/fileguard.py
fileguard/utils.py
fileguard-0.0.1.dist-info/METADATA
fileguard-0.0.1.dist-info/RECORD
fileguard-0.0.1.dist-info/WHEEL
fileguard-0.0.1.dist-info/top_level.txt
