Metadata-Version: 2.1
Name: fileguard
Version: 0.0.1
Summary: Preserve the content of your files and directories during testing.
Home-page: https://github.com/iluxonchik/fileguard
Author: Illya Gerasymchuk
Author-email: illya@iluxonchik.me
License: MIT
Keywords: testing,testing tools,test,file,directory,preserve content,backup
Platform: UNKNOWN
Classifier: Programming Language :: Python :: 3.6
Classifier: Programming Language :: Python :: 3.7
Classifier: Intended Audience :: Developers
Classifier: License :: OSI Approved :: MIT License
Classifier: Operating System :: OS Independent
Classifier: Topic :: Software Development :: Testing
Classifier: Topic :: Software Development :: Testing :: Unit
